Grampo/__init__.py
Grampo/app.py
Grampo/config.py
Grampo/td/__init__.py
Grampo/td/account.py
Grampo/td/auth.py
Grampo/td/configs.py
Grampo/td/mtp.py
Grampo/td/shared.py
Grampo/td/storage.py
Grampo/td/tdesktop.py
Grampo/tl/__init__.py
Grampo/tl/configs.py
Grampo/tl/shared.py
Grampo/tl/telethon.py
Grampo/ut/Storage.py
Grampo/ut/__init__.py
Grampo/ut/api.py
Grampo/ut/debug.py
Grampo/ut/devices.py
Grampo/ut/exception.py
Grampo/ut/utils.py
grampo-1.0.0.dist-info/METADATA
grampo-1.0.0.dist-info/WHEEL
grampo-1.0.0.dist-info/top_level.txt
grampo-1.0.0.dist-info/RECORD
