Metadata-Version: 2.4
Name: Grampo
Version: 1.0.0
Summary: A Python Telegram API Library , with official Telegram APIs.
Home-page: https://github.com/abbas-bachari/Grampo
Author: Abbas Bachari
Author-email: abbas-bachari@hotmail.com
License: MIT
Project-URL: Homepage, https://github.com/abbas-bachari/Grampo
Project-URL: Documentation, https://github.com/abbas-bachari/Grampo
Project-URL: Source, https://github.com/abbas-bachari/Grampo/
Project-URL: Tracker, https://github.com/abbas-bachari/Grampo/issues
Keywords: telethon,telegram,telegram multi session,telegram-python,opentele,api,abbas bachari
Classifier: Intended Audience :: Developers
Classifier: Topic :: Software Development :: Libraries :: Python Modules
Classifier: License :: OSI Approved :: MIT License
Classifier: Operating System :: OS Independent
Classifier: Programming Language :: Python :: 3
Requires-Python: >=3.10
Requires-Dist: loguru
Requires-Dist: PyQt5
Requires-Dist: TgCrypto
Requires-Dist: telethon
Requires-Dist: psutil
Requires-Dist: python-socks[asyncio]
Dynamic: author
Dynamic: author-email
Dynamic: classifier
Dynamic: description
Dynamic: description-content-type
Dynamic: home-page
Dynamic: keywords
Dynamic: license
Dynamic: project-url
Dynamic: requires-dist
Dynamic: requires-python
Dynamic: summary
